octowire/__init__.py
octowire/gpio.py
octowire/i2c.py
octowire/logic.py
octowire/mci.py
octowire/octowire.py
octowire/pwm.py
octowire/spi.py
octowire/time.py
octowire/uart.py
octowire/uled.py
octowire/utils/Colors.py
octowire/utils/Logger.py
octowire/utils/__init__.py
octowire/utils/serial_utils.py
octowire_lib-1.0.5.dist-info/LICENSE
octowire_lib-1.0.5.dist-info/METADATA
octowire_lib-1.0.5.dist-info/WHEEL
octowire_lib-1.0.5.dist-info/top_level.txt
octowire_lib-1.0.5.dist-info/zip-safe
octowire_lib-1.0.5.dist-info/RECORD
