Metadata-Version: 2.1
Name: octowire-lib
Version: 1.0.5
Summary: Octowire library
Home-page: https://github.com/immunIT/octowire-lib/
Author: Jordan Ovrè, Paul Duncan
License: Apache 2.0
Download-URL: https://github.com/immunIT/octowire-lib/archive/1.0.2.tar.gz
Keywords: octowire,library,hardware,security,pentest
Platform: UNKNOWN
Classifier: Intended Audience :: Developers
Classifier: License :: OSI Approved :: Apache Software License
Classifier: Programming Language :: Python :: 3
Classifier: Development Status :: 5 - Production/Stable
Requires-Python: >=3.7
Requires-Dist: pyserial (<4,>=3.4)
Requires-Dist: beautifultable (==1.0.0)
Requires-Dist: colorama ; platform_system == "Windows"
